README.md
setup.py
data_diger.egg-info/PKG-INFO
data_diger.egg-info/SOURCES.txt
data_diger.egg-info/dependency_links.txt
data_diger.egg-info/requires.txt
data_diger.egg-info/top_level.txt
data_diger/base/__init__.py
data_diger/base/common.py
data_diger/selenium/__init__.py
data_diger/selenium/common.py