Metadata-Version: 2.4
Name: data-diger
Version: 0.1.1
Summary: Useful tools
Author: Andrey Plugin
Author-email: 9keepa@gmail.com
License: MIT
Requires-Python: >=3.10.12
Requires-Dist: selenium-stealth-fork
Dynamic: author
Dynamic: author-email
Dynamic: description
Dynamic: description-content-type
Dynamic: license
Dynamic: requires-dist
Dynamic: requires-python
Dynamic: summary
